twine_graph/__init__.py
twine_graph/__main__.py
twine_graph/twine_graph.py
twine_graph-0.0.1.dist-info/METADATA
twine_graph-0.0.1.dist-info/RECORD
twine_graph-0.0.1.dist-info/WHEEL
twine_graph-0.0.1.dist-info/entry_points.txt
twine_graph-0.0.1.dist-info/top_level.txt
