Metadata-Version: 2.1
Name: twine-graph
Version: 0.0.1
Summary: A utility for parsing HTML Twine stories and saving
Home-page: https://github.com/ehenestroza/twine-graph
Author: Enrique Henestroza Anguiano
Author-email: ehenestroza@gmail.com
License: UNKNOWN
Platform: UNKNOWN
Classifier: License :: OSI Approved :: GNU General Public License v3 (GPLv3)
Classifier: Programming Language :: Python :: 3.4
Classifier: Programming Language :: Python :: 3.5
Classifier: Programming Language :: Python :: 3.6
Classifier: Programming Language :: Python :: 3.7
Classifier: Programming Language :: Python :: 3.8
Requires-Dist: beautifulsoup4
Requires-Dist: graphviz
